{"/+pz6LdX1BMzJdenUZU0VQ==":"luxury-hub-236x128.png","urj/UEuAnOUiOKAm2ZkWjQ==":"9-2000x1337.jpg","QQStur1/t9l/bnrxhsfCUg==":"haya-permanent-residency-permit-2000x1662.png","jVCFU59wBJr1R/0yYo1C4Q==":"623874-1400x865.jpg","/Dm6Dsg2AhgObwAJhXIprQ==":"%D8%A7%D8%B4%D8%BA%D8%B4-%D9%82%D8%AB%D8%B3%D9%87%D9%8A%D8%AB%D9%89%D9%81-2000x1662.png","yS/UYrDygdOq8ZCs2Derng==":"eu-citizen-2000x1662.jpg","1nJ3NjmcPHpxodxC1ZhWDQ==":"eu-citizen-1-2000x1662.jpg","d1XmH3cWbKat2oHgG1N9rA==":"eu-citizen-2-2000x1662.jpg","DRtCQ5rDo0Vib0ZaWTRl8w==":"live-in-eu-2000x1662.jpg","zytM7ePplZKkgbWp8hBAlg==":"eu-haya-resident-2000x1648.jpg","YFf7MsrNFTQSskdUBX6T5A==":"haya-luxury-resident-1400x760.png","d+ldquNAVBRTf372DL3l6w==":"mockup-king-3d-02-(1)-2000x1338.jpg","v6m8V95948czYsNKMZgPfA==":"fotolia-2000x1474.jpg","ZrUOUXFAEB0D5btPz1TzEQ==":"fotolia-2000x1328.jpg","eTGUDQqB2SXpSrYHIEK1fg==":"foil-stamp-2000x1484.jpg","2HOetwQyPRbjlnwh6z8x5g==":"apple_z0rm_mjy321_12_macbook_early_2015-1400x1400.jpg","jLvFroBL0B/NbvFz3FpvqQ==":"imac-storage-hero-1400x3856.png","N3VHy+32exm4VCmmQwybhw==":"laptop-front3-1400x1205.png","kMbhp5ZFn2QYYYOGxb132A==":"metal-stamp-2000x1384.jpg","3LYCLx6C0tQEDxCpUSgIVA==":"layer-0-copy11-1400x988.jpg","88KSRnRmlrvF+7kr2gDS7g==":"1200x-1dd-1400x787.jpg","0ZUtsagMyFTM0qo2LoAIOw==":"623874-600x371.jpg","h9qLpQ7Ovho4APoCr2r+XA==":"background-600x399.jpg","FmA/QmpSnxEbmmq4jWBeig==":"business%20solutions%20online-600x337.jpg","OvCLlDa1ylY0HWu+hyrglw==":"%D8%A7%D9%84%D8%A7%D8%B3%D8%AA%D8%AB%D9%85%D8%A7%D8%B1%20%D9%81%D9%8A%20%D9%82%D8%A8%D8%B1%D8%B5%20%D9%84%D9%8A%D9%85%D8%A7%D8%B3%D9%88%D9%84-600x371.jpg","RoUH2Bd56g888+8JW+FHUQ==":"yachting12-at-limassol-marina-2000x1224.jpg","5t9NRx5HSLklKfRM+kyhFw==":"limassol-marina-2000x1172.jpg","tyG1/SrG9Sf8BSkfc7yZFw==":"1029523-600x377.jpg","ms8kIDwNQtnBgHtwNHputQ==":"bigstock-travel-concept-600x400.jpg","3gjv0Qu5z3w02Fn4laOTxg==":"2335-2000x1313.jpg","+fipvNwhXpzsUrtzfwew3A==":"i-600x343.jpg","rq3MXC2QCTxugbRSiiUPfw==":"luxury-hsub-128x128.png","3roy3+0eCZuluK5jj6Mh+Q==":"ssss-128x128.jpg","rVrbBEGbIm5WdOzKE+UJUw==":"logo-vertical-on-white-128x176.png","9OYLyhYD9DUGyy0qJnNa7g==":"63725_63725_vi-372_img_00_0002_max_656x437-600x449.jpg","odInf6e+HLSyB/WVmFsAzw==":"14533-first-exclusive-villas-at-limassol-marina-reach-completion-600x399.jpg","5aZLDHP9wX5IoFwNZkJuag==":"pink-slip-1400x935.jpg","Ml88qk42CmPVY+ZhcYNPsQ==":"98429_98429_idh3577_img_00_0000_max_656x437-600x449.jpg","nWDj4n9LCOIP5XmZd6gJaA==":"shutterstock-1400x1050.jpg","NqBl8vpLRpDFnyct7y3nVQ==":"ihome_loc700-2000x1500.jpg","iJi1i9dRKcpzK1MUJjKA0g==":"17124-2000x1315.jpg","RObkL5Mi27Fp3JNc6bEM8w==":"7-2000x1249.jpg","bEK5ptnHADytr1D1CA5t8w==":"61271847-2000x1333.jpg","X660VPGj+Q8FJ0lNQObZAg==":"feature-andria-main-pic-leptos-developers-limassol-del-mar-770x326-2000x1352.jpg","1FGb4eMFA/zIB5cSXqoAOA==":"hgg-2000x1233.jpg","g7YaLcckSzhKCacI2fJyhw==":"maxresdefault-2000x1125.jpg","EI3RFgHaG4zurHU5IlstVQ==":"141338_141338_v2463_img_00_0000_max_656x437-2000x1334.jpg","dhIuAbQ+R7471etXtYu6ew==":"63725_63725_vi-372_img_00_0002_max_656x437-2000x1499.jpg","i35obdwy8lMR49rUKe/gpw==":"ihv9-night_res-2000x1500.jpg","mCc0L3pNcpPUojq/eWxhng==":"fotolia_145704429_subscription_monthly_xl-600x300.jpg","Kw1AtTXB95ojj2R0wbPvKw==":"fotolia_149951341_subscription_monthly_xl-600x345.jpg","Fy691spjwDBe8HxQEIcMxw==":"ukif-600x328.jpg","Pas+EJsVIKTcYRY5QTeHlQ==":"18619966_1389816134399196_2228410157068748747_n-600x400.jpg","qlsBocj2xG1EnllymRt7iQ==":"18671049_1389816404399169_4064185206562450580_n-600x400.jpg","2veWN3y+LaxCBxt/4KCGog==":"portugal_lisbon-2000x1500.jpg","3FvEalw4HeTZ5MTBwffzbQ==":"shutterstock-600x400.jpg","WjfIKZ1yLZSUx35s8qdVGw==":"hgg-600x370.jpg","TNs/WVWS/BvCwoen5CtVlg==":"fotolia_123363749_subscription_monthly_xxl-600x397.jpg","tNNtZjRCw589dxAoCuk7ag==":"maxresdefault-1-2000x1125.jpg","LkO5By8JiAY9+6McsbtP+A==":"dom-camilo-strand-algarve-lagos-2000x1086.jpg","XGVvjViQYn+2TcWUmQcN7g==":"fotolia_137052068_subscription_monthly_xxl-1400x927.jpg","0ThF1Ml13IhG5erynCEBgA==":"7065230ad9fe0e846f902db49278f057-2000x677.jpg","5Kfj6IW8MLfoxDDGXwyWEQ==":"1635-2000x1313.jpg","aiSG1VyX1vhVNBvuFyICzg==":"kelley-house-main-2000x1483.jpg","8TX0vC87dENLKS3gu254mA==":"logo-horizontal-265x76.png","CdpF/lZNWdcsj8NmBEoG6Q==":"fotolia-145704429-subscription-monthly-xl-1-600x300.jpg","jwCOkRPvwDG0B7CAdXPPyQ==":"1029523-1-600x377.jpg","A8uRaMw7u8FXw4J7kQWrLw==":"fotolia-145704429-subscription-monthly-xl-2-600x300.jpg","30laBNMAdC5vgLJbKj+Uhg==":"business-solutions-online-1-600x337.jpg","4JC9ItxakYl2Kb1PIKg+wA==":"-1-600x371.jpg","6ke3sOa0ZQBw6IEs88eNLA==":"shutterstock-40024216-600x398.jpg","24oJUPwOIklihSh9KCqNOg==":"3-600x394.png","w2WTx3lMei1ap8hQc3o1NQ==":"hd-greece-wallpaper-24834-25507-hd-wallpapers-600x375.jpg","/j8EkIusLbkGx3heCy8GZw==":"haya-permanent-residency-permit-2000x1662.png","uUf7P044tZ6skgMaJ2mhwA==":"-2000x1662.png","U36dnB9W872/wYpph4Xr6w==":"12039245_1653957211547385_7936442226111319361_n-600x421.jpg","No/mT6WiH2N1ZsAHaY0itA==":"1280x720-data-out-154-69516390-portugal-wallpapers-600x338.jpg","fz6fMN51CGKzE62i8HD49w==":"14590042_1862079067358757_6913068731818099601_o-600x401.jpg","6KQOg0+BwYBNLXiVpydNCw==":"14937378_1869221983311132_7881689930705543891_n-600x412.jpg","eigIZHGwJ8/Et71Jy87AVg==":"shutterstock-135894941-600x400.png","tranx47xIQ/ZBcf0E2XAow==":"1280x720-data-out-154-69516390-portugal-wallpapers-1-600x338.jpg","awqEToZdixU+BOZCNfljcw==":"1280x720-data-out-154-69516390-portugal-wallpapers-2-600x338.jpg","AtUyudAwDSit4KUsE1HBPQ==":"dom_luis_bridge-600x400.jpg","7s3CAgCW/YM2sKipk3gVUw==":"17434653_1381266648599383_3984141783030003892_o-600x376.jpg","94lqwgPjpGiFvutdEMd94Q==":"st-georges-grenada-600x333.jpg","LGIYmkj836jfgtBI7GoqpA==":"17310389_1381266645266050_7578290783704982136_o-600x399.jpg","THlLkPjRymeSY1Pbv53VEA==":"17434653_1381266648599383_3984141783030003892_o-1-600x376.jpg","WnpcE4htZ/IW2tB72n4VQg==":"17434653_1381266648599383_3984141783030003892_o-2-600x376.jpg","BRCw4/Xgsw7JSZ5yehBjVw==":"shutterstock-599655725-600x249.png","xkuNUx9ceS5NcP6FXC3TAw==":"vienna_austria_capital_travel_view_from_above_97973_1920x1080-600x338.jpg","pQiIaS5EIub1HvKdh/Z3rg==":"vienna_austria_capital_travel_view_from_above_97973_1920x1080-1-600x338.jpg","5Raso/q75bHIXHQkb5jDkw==":"vienna_austria_capital_travel_view_from_above_97973_1920x1080-2-600x338.jpg","22Nc+cEiAToIiZrlu1hk1A==":"shutterstock-599655725-1000x415.png","7Ixn0ljZp4+ByvqqyiuyyQ==":"wp2386087-1920x1200.jpg","g7rF68NIH28z1dKLrlRx0g==":"turkish%20citizenship%20by%20investment-1000x667.png","91bsFJgHuGRG0ZDc6lo/eQ==":"istanbul-8-2000x1125.jpg","CfWAEbFvb+KUjwS/jetfXg==":"%D8%AA%D8%B1%D9%83%D9%8A%D8%A7-1920x1200.jpg","9J2IdmaVTyzC4bqE0e1peQ==":"istanbul-2-2000x1333.jpg","F1AeEoJKS2xlsUI2CfAj3w==":"istanbul-3-1920x1080.jpg","WoZ1y1BoCGIbJXL+NTA1lQ==":"istanbul-4-1920x1080.jpg","ItpPJShFcH2Us3Bbkb6wbQ==":"istanbul-5-1920x1080.jpg","XeizeId9CjrwKeuyiDGF7Q==":"wp2386137-1920x1200.jpg","NxYOFhIACT1xmx0SquKK5w==":"turkish-citizenshipby-investment-1000x667.png","H28cn729npH7pMllX2r39A==":"turkish-citizenship-by-investment-1000x667.png","Jhq/i+B0zRtZuu6+YTsHTw==":"sea-view-roomy-houses-near-all-facilities-in-istanbul-turkey-4-1400x800.jpg","VnfUDcASBYil9GNZU6sykA==":"istanbul-3-2000x1333.jpg","Nde2svbcUYFJcNz2dB6RJg==":"turkish-citizenship-by-investment-1-1000x667.png","GCXFGivaaovt8doUwUY86g==":"sea-view-roomy-houses-near-all-facilities-in-istanbul-turkey-5-1400x800.jpg","Bw76LcI1D72m1jSQJYsJUQ==":"istanbul-3-1920x1080-800x450.jpg","yVjHwFXekdufww/tQn0HGQ==":"istanbul-3-800x450.jpg","N0jWfnxi8S1g4mPeaCi9xg==":"17434653_1381266648599383_3984141783030003892_o-1000x627.jpg","Pi/EvxiHXsWP3mrf8abUcg==":"kepinski-917x516.jpg","6LA4RI8xW2knhJOHCXqj+w==":"dominica-1110x550.jpg","9gEfvTOw7G2TRBNCvw52UA==":"domnca-citizenship-by-investment-1000x667.png","anlC8BlvToQIL1kCX8ji0Q==":"56-4000093-1446832566b4f880f6d26a489cadfc2ee911f95b76-768x429.jpg","OK54uSuDZ9sB2urv3uuCbw==":"shutterstock-426891166-1000x656.png","hb57Vo74a+84SSYPYWFjKw==":"dom_hero-1521572045-1200x750.jpg","7Z9jXoZVts2a7wBXRdjISg==":"download-1108x693.jpg","61Tawk/xphTCOP+1NDaHMA==":"56-4000093-1446832566b4f880f6d26a489cadfc2ee911f95b76-1-768x429.jpg","wbEAmkOT4mjDl/88aMKF4w==":"56-4000093-1446832566b4f880f6d26a489cadfc2ee911f95b76-2-768x429.jpg","Fdoje/IhoheOYt+a3oW5ng==":"domnca-citizenship-by-investment-1-1000x667.png","PjIs+7VGeY98MGbJgqnrKg==":"caribbean-291012_960_720-e1522408206488-640x480.jpg","PlDxImlUf2pBdx4Xe/OdYw==":"06dfacb0c35dcdaeea92f05e0bbc9d790093e393-1400x933.jpg","SIaDpBAsjzviY3YCt3+T7Q==":"photodune-2469534-businessman-in-front-of-private-jet-xs-594x336.jpg","JuVwD/Zx0/Vjrz44G0kweQ==":"dom_hero-1521572046-1200x750.jpg","5hUfi1LNNrP40QATuwCYfw==":"download-1-1108x693.jpg","jUwo5bdIuC0GKcPX6sacFw==":"dom_hero-1521572047-1200x750.jpg","IeHmijJx7y+NLKK9XurKqg==":"download-2-1108x693.jpg","G6SJ7hEnzpvPIzLt7S607g==":"roseau-dominica-news-online-1370x911.jpg","CYsG6dvVG4T0wnL5hpb7cw==":"roseau-dominica-news-online-1-1370x911.jpg","4Qp0bCeW1h4kl+u+I6HK4A==":"dom_luis_bridge-1-600x400.jpg","dv7iEvoGWOxoLAMzV/xm7g==":"14590042_1862079067358757_6913068731818099601_o-1-600x401.jpg","hoEH9o/0ttdYAWfnCIxYHg==":"austria-residency-1000x667.png","troQiQGNhpiQKqBaw4Dj+w==":"austria-wallpapers-10-1931x1091.jpg","Qan3B3+C6nGvox/ExFqalA==":"belvedere_palace_vienna_austria_winter-wallpaper-1920x1440.jpg","zj041pQ41iY5jcE0Aemyfw==":"863808-widescreen-austria-wallpapers-1920x1200-for-lockscreen-1920x1200.jpg","UrQaGof4GwSnZG7io+aEBQ==":"1-852x480.jpg","5tOnzy9/G0hdovsvpFfoiw==":"austria-wallpapers-5-1931x1091.jpg","7289LE2BAnby8EjG+etBVw==":"austria-residency-1-1000x667.png","kTYQ7uF24IgtQVv4gkE/OQ==":"austria-wallpapers-6-1931x1091.jpg","kgVHbHRFxzyVmcksJbBdnw==":"vienna-austria-desktop-wallpaper-600x338.jpg","ItZ53YBFHEdAJVGV56mfPg==":"belvedere_palace_vienna_austria_winter-wallpaper-600x450.jpg","j1cOSj8yOHvTibpO6lZEQA==":"citizenship-by-investment.in-grenada-1000x667.png","BfWha5U7KB2g8iAbeumpDg==":"120126043053-grenada-caribbean-4-horizontal-large-gallery-760x428.jpg","VnMoSzW25p+pwJAtTZ4ENg==":"02-grenada-st-george-port-louis-1185x784.jpg","g2WplxaO4Mge80hbSyJsAQ==":"st-georges-grenada-1024x569.jpg","pZs//7uL4QxqIRhOjWCxqQ==":"shutterstock-1022357479-1000x665.png"}